{
    "$schema": "../../../schemas/collectible.json",
    "speed": "${vec2(randomf(-100, 100), randomf(-125, -50)+randomf(-125, -50))}",
    "acceleration": "${vec2(0, 400)}",
    "particle": "particles/powerup_speed_shot.json",
    "pickupParticle": "particles/powerup_catch.json",
    "spawnSound": "sound_events/spawn_powerup.json",
    "pickupSound": "sound_events/catch_powerup_shot_speed.json",
    "pickupName": "SPEED SHOT!",
    "pickupFont": "fonts/score0.json",
    "effects": [
        {
            "type": "speedShot",
            "time": 20,
            "speed": 1500
        }
    ]
}