{
    "$schema": "../../../schemas/sphere.json",
    "sprites": [
        {
            "sprite": "sprites/game/ball_fire.json",
            "animationSpeed": 16,
            "rotate": false
        }
    ],
    "shadowSprite": "sprites/game/ball_shadow.json",
    "idleParticle": "particles/idle_ball_bomb.json",
    "destroyParticle": "particles/collapse_ball_bomb.json",
    "colorPalette": "color_palettes/powerups/fire_pal.json",
    "colorPaletteSpeed": 64,
    "swappable": true,
    "shotBehavior": {
        "type": "normal"
    },
    "shotSound": "sound_events/launch_fireball.json",
    "hitBehavior": {
        "type": "destroySpheres",
        "selector": "sphere_selectors/fireball.json",
        "scoreEvent": "score_events/fireball.json"
    },
    "hitSound": "sound_events/collapse_fireball.json",
    "matches": [
        -1,
        1,
        2,
        3,
        4,
        5,
        6,
        7,
        10
    ]
}